ambition_visit_schedule/__init__.py
ambition_visit_schedule/apps.py
ambition_visit_schedule/constants.py
ambition_visit_schedule/tests/__init__.py
ambition_visit_schedule/tests/static_schedule.py
ambition_visit_schedule/tests/test_schedule.py
ambition_visit_schedule/tests/urls.py
ambition_visit_schedule/visit_schedules/__init__.py
ambition_visit_schedule/visit_schedules/crfs.py
ambition_visit_schedule/visit_schedules/requisitions.py
ambition_visit_schedule/visit_schedules/schedule.py
ambition_visit_schedule/visit_schedules/schedule_w10.py
ambition_visit_schedule/visit_schedules/visit_schedule.py
ambition_visit_schedule-0.1.27.dist-info/AUTHORS
ambition_visit_schedule-0.1.27.dist-info/LICENSE
ambition_visit_schedule-0.1.27.dist-info/METADATA
ambition_visit_schedule-0.1.27.dist-info/WHEEL
ambition_visit_schedule-0.1.27.dist-info/top_level.txt
ambition_visit_schedule-0.1.27.dist-info/RECORD
