Metadata-Version: 2.1
Name: ambition-visit-schedule
Version: 0.1.27
Summary: Visit schedule for ambition/edc project
Home-page: https://github.com/ambition-trial/ambition-visit-schedule
Author: Erik van Widenfelt
Author-email: ew2789@gmail.com
License: GPL license, see LICENSE
Keywords: ambition visit schedule
Platform: UNKNOWN
Classifier: Environment :: Web Environment
Classifier: Framework :: Django
Classifier: Intended Audience :: Developers
Classifier: Intended Audience :: Science/Research
Classifier: License :: OSI Approved :: GNU General Public License v3 (GPLv3)
Classifier: Operating System :: OS Independent
Classifier: Programming Language :: Python :: 3.7
Classifier: Topic :: Internet :: WWW/HTTP
Classifier: Topic :: Internet :: WWW/HTTP :: Dynamic Content
Requires-Python: >=3.7
Requires-Dist: ambition-labs
Requires-Dist: ambition-sites
Requires-Dist: edc-visit-schedule
